raducord/__init__.py
HeaderUtils-1.0.1.dist-info/LICENSE
HeaderUtils-1.0.1.dist-info/METADATA
HeaderUtils-1.0.1.dist-info/WHEEL
HeaderUtils-1.0.1.dist-info/top_level.txt
HeaderUtils-1.0.1.dist-info/RECORD
